markdown_editor/__init__.py
markdown_editor/server.py
markdown_editor/core/__init__.py
markdown_editor/core/agent.py
markdown_editor/core/config_loader.py
markdown_editor/core/document.py
markdown_editor/core/engine.py
markdown_editor/core/llm_client.py
markdown_editor/core/models.py
markdown_editor/core/parser.py
markdown_editor/core/path_utils.py
markdown_editor/tools/__init__.py
markdown_editor/tools/edit_tools.py
markdown_editor/tools/file_ops.py
markdown_editor_mcp_server-0.1.7.dist-info/licenses/LICENSE
markdown_editor_mcp_server-0.1.7.dist-info/METADATA
markdown_editor_mcp_server-0.1.7.dist-info/WHEEL
markdown_editor_mcp_server-0.1.7.dist-info/entry_points.txt
markdown_editor_mcp_server-0.1.7.dist-info/top_level.txt
markdown_editor_mcp_server-0.1.7.dist-info/RECORD
