Metadata-Version: 2.4
Name: markdown-editor-mcp-server
Version: 0.1.7
Summary: MCP server for structured text editing in Markdown files
Author: Artem K
License: MIT
Project-URL: Repository, https://github.com/KazKozDev/markdown-editor-mcp-server
Project-URL: Issues, https://github.com/KazKozDev/markdown-editor-mcp-server/issues
Project-URL: Changelog, https://github.com/KazKozDev/markdown-editor-mcp-server/blob/main/CHANGELOG.md
Keywords: mcp,model-context-protocol,markdown,editor,agentic-editing,llm,claude,ollama
Classifier: Development Status :: 4 - Beta
Classifier: Intended Audience :: Developers
Classifier: License :: OSI Approved :: MIT License
Classifier: Programming Language :: Python :: 3
Classifier: Programming Language :: Python :: 3.10
Classifier: Programming Language :: Python :: 3.11
Classifier: Programming Language :: Python :: 3.12
Classifier: Topic :: Text Processing :: Markup :: Markdown
Classifier: Topic :: Software Development :: Libraries :: Python Modules
Requires-Python: >=3.10
License-File: LICENSE
Requires-Dist: mcp>=0.9.0
Requires-Dist: pyyaml>=6.0.1
Dynamic: license-file
